fraplib/__init__.py
fraplib/_setupfunction.py
fraplib/attachments.py
fraplib/bkgdsubtract.py
fraplib/calculations.py
fraplib/circular_mask.py
fraplib/expb2.py
fraplib/falsecolor.py
fraplib/filter_labels.py
fraplib/loading.py
fraplib/metadatafunctions.py
fraplib/onestep.py
fraplib/pretty_plot.py
fraplib/read_chromatogram.py
fraplib/regions.py
fraplib/scalebar.py
fraplib/threshold.py
fraplib/timestamp.py
fraplib-0.1.1.dist-info/METADATA
fraplib-0.1.1.dist-info/WHEEL
fraplib-0.1.1.dist-info/licenses/LICENSE
fraplib-0.1.1.dist-info/RECORD
