Metadata-Version: 2.1
Name: fraplib
Version: 0.1.1
Project-URL: Homepage, https://github.com/emay2022/fraplib
Project-URL: Documentation, https://github.com/emay2022/fraplib#fraplib
Project-URL: Repository, https://github.com/emay2022/fraplib.git
Author-email: Elizabeth May <ejmay2012@gmail.com>
License: BSD 3-Clause License
License-File: LICENSE
Classifier: Development Status :: 4 - Beta
Classifier: Intended Audience :: Developers
Classifier: Intended Audience :: Science/Research
Classifier: License :: OSI Approved :: BSD License
Classifier: Operating System :: OS Independent
Classifier: Programming Language :: Python
Classifier: Programming Language :: Python :: 3
Classifier: Programming Language :: Python :: 3.8
Classifier: Programming Language :: Python :: 3.9
Classifier: Programming Language :: Python :: 3.10
Classifier: Programming Language :: Python :: 3.11
Requires-Python: >=3.7
Requires-Dist: czifile
Requires-Dist: matplotlib
Requires-Dist: numpy
Requires-Dist: pandas
Requires-Dist: scipy
Requires-Dist: symfit
Requires-Dist: xarray
Provides-Extra: fancyplotting
Requires-Dist: mpl-interactions; extra == 'fancyplotting'
